README.md
setup.cfg
setup.py
jaxrk/__init__.py
jaxrk.egg-info/PKG-INFO
jaxrk.egg-info/SOURCES.txt
jaxrk.egg-info/dependency_links.txt
jaxrk.egg-info/requires.txt
jaxrk.egg-info/top_level.txt
jaxrk/kern/__init__.py
jaxrk/kern/base.py
jaxrk/rkhs/__init__.py
jaxrk/rkhs/base.py
jaxrk/rkhs/operator.py
jaxrk/rkhs/sp_vector.py
jaxrk/rkhs/vector.py
jaxrk/utilities/__init__.py
jaxrk/utilities/array_manipulation.py
jaxrk/utilities/defaults.py